CHANGES.txt
LICENSE.txt
MANIFEST.in
README.txt
django_inoa.egg-info/PKG-INFO
django_inoa.egg-info/SOURCES.txt
django_inoa.egg-info/dependency_links.txt
django_inoa.egg-info/requires.txt
django_inoa.egg-info/top_level.txt
inoa/__init__.py
inoa/admin/__init__.py
inoa/admin/change_actions.py
inoa/admin/fk_link.py
inoa/admin/safe_bulk_delete.py
inoa/backends/__init__.py
inoa/backends/detour_email_backend.py
inoa/backends/email_auth_backend.py
inoa/forms/__init__.py
inoa/http/__init__.py
inoa/http/responses.py
inoa/middleware/__init__.py
inoa/models/__init__.py
inoa/models/formatter.py
inoa/models/managers.py
inoa/models/parent_model.py
inoa/models/utils.py
inoa/models/fields/__init__.py
inoa/models/fields/cpf.py
inoa/settings/__init__.py
inoa/settings/settings_loader.py
inoa/tastypie/__init__.py
inoa/tastypie/resources.py
inoa/templatetags/__init__.py
inoa/templatetags/absurl.py
inoa/utils/__init__.py
inoa/utils/date_to_utc.py
inoa/utils/generic_object.py
inoa/utils/json.py
inoa/utils/method_cache.py
inoa/utils/profiling.py
inoa/views/__init__.py
inoa/views/ajaxview.py