Metadata-Version: 1.0
Name: django-inoa
Version: 0.2.9
Summary: Collection of django tools and snippets commonly used by Inoa.
Home-page: https://bitbucket.org/inoa/django-inoa
Author: Inoa
Author-email: django@inoa.com.br
License: LICENSE.txt
Platform: UNKNOWN
Classifier: Development Status :: 4 - Beta
Classifier: Framework :: Django
Classifier: Intended Audience :: Developers
Classifier: Topic :: Utilities
Classifier: License :: OSI Approved :: BSD License
